gitlab_ci_cd_variables_tree/__init__.py
gitlab_ci_cd_variables_tree/cli.py
gitlab_ci_cd_variables_tree/core.py
gitlab_ci_cd_variables_tree/styles.py
gitlab_ci_cd_variables_tree-0.1.0.dist-info/entry_points.txt
gitlab_ci_cd_variables_tree-0.1.0.dist-info/WHEEL
gitlab_ci_cd_variables_tree-0.1.0.dist-info/METADATA
gitlab_ci_cd_variables_tree-0.1.0.dist-info/RECORD
