Metadata-Version: 2.1
Name: gitlab-ci-cd-variables-tree
Version: 0.1.0
Summary: Show Gitlab CI/CD variables as Tree structure
Home-page: https://github.com/f9n/gitlab-ci-cd-variables-tree
License: GPL-3.0
Author: Fatih Sarhan
Author-email: f9n@protonmail.com
Requires-Python: >=3.9,<4.0
Classifier: License :: OSI Approved :: GNU General Public License v3 (GPLv3)
Classifier: Programming Language :: Python :: 3
Classifier: Programming Language :: Python :: 3.10
Classifier: Programming Language :: Python :: 3.9
Requires-Dist: click (>=8.0.3,<9.0.0)
Requires-Dist: python-gitlab (>=3.1.0,<4.0.0)
Requires-Dist: rich (>=11.0.0,<12.0.0)
Project-URL: Repository, https://github.com/f9n/gitlab-ci-cd-variables-tree
